{
  "palette": [
    { "num": "01", "label": "Blanc", "color": "#f6f8fa" },
    { "num": "02", "label": "Crème", "color": "#ffe9c2" },
    { "num": "03", "label": "Jaune", "color": "#f5d200" },
    { "num": "04", "label": "Orange", "color": "#ed560f" },
    { "num": "05", "label": "Rouge", "color": "#c52125" },
    { "num": "06", "label": "Rose", "color": "#f6859b" },
    { "num": "07", "label": "Violet", "color": "#583785" },
    { "num": "08", "label": "Bleu foncé", "color": "#004f9d" },
    { "num": "09", "label": "Bleu", "color": "#016daf" },
    { "num": "10", "label": "Vert", "color": "#00823a" },
    { "num": "11", "label": "Vert clair", "color": "#37b085" },
    { "num": "12", "label": "Marron", "color": "#492b22" },
    { "num": "13", "label": "Rouge transparent", "color": "#af0e1a" },
    { "num": "14", "label": "Jaune transparent", "color": "#f3c902" },
    { "num": "15", "label": "Bleu transparent", "color": "#027fcd" },
    { "num": "16", "label": "Vert transparent", "color": "#069d68" },
    { "num": "17", "label": "Gris", "color": "#848c8b" },
    { "num": "18", "label": "Noir", "color": "#080301" },
    { "num": "19", "label": "Transparent", "color": "#d2dce4" },
    { "num": "20", "label": "Caramel", "color": "#7a2c1d" },
    { "num": "21", "label": "Marron clair", "color": "#c65d1d" },
    { "num": "22", "label": "Rouge noël", "color": "#b61625" },
    { "num": "24", "label": "Violet transparent", "color": "#44427b" },
    { "num": "26", "label": "Rose mat", "color": "#e0b098" },
    { "num": "27", "label": "Beige", "color": "#edc89c" },
    { "num": "28", "label": "Vert foncé", "color": "#3a5240" },
    { "num": "29", "label": "Lie-de-vin", "color": "#da2f5d" },
    { "num": "30", "label": "Bordeaux", "color": "#572c30" },
    { "num": "31", "label": "Turquoise", "color": "#80bdcb" },
    { "num": "32", "label": "Fuchsia néon", "color": "#d31d63" },
    { "num": "33", "label": "Cerise", "color": "#d51a32" },
    { "num": "34", "label": "Jaune néon", "color": "#ecdc35" },
    { "num": "35", "label": "Rouge néon", "color": "#dd1d2d" },
    { "num": "36", "label": "Bleu néon", "color": "#0081c6" },
    { "num": "37", "label": "Vert néon", "color": "#60aa4a" },
    { "num": "38", "label": "Orange néon", "color": "#ec8006" },
    { "num": "42", "label": "Vert fluorescent", "color": "#4faa34" },
    { "num": "43", "label": "Jaune pastel", "color": "#f0df39" },
    { "num": "44", "label": "Rouge pastel", "color": "#d9594f" },
    { "num": "45", "label": "Violet pastel", "color": "#9886b1" },
    { "num": "46", "label": "Bleu pastel", "color": "#32b1e8" },
    { "num": "47", "label": "Vert pastel", "color": "#8bc363" },
    { "num": "48", "label": "Rose pastel", "color": "#e689bb" },
    { "num": "49", "label": "Azure", "color": "#6dc0c0" },
    { "num": "60", "label": "Marron nounours", "color": "#f29d0e" },
    { "num": "70", "label": "Gris clair", "color": "#afc0cb" },
    { "num": "71", "label": "Gris foncé", "color": "#494f53" },
    { "num": "72", "label": "Rose transparent", "color": "#eb9cb7" },
    { "num": "73", "label": "Bleu transparent", "color": "#0290c4" },
    { "num": "74", "label": "Lilas transparent", "color": "#7255a0" },
    { "num": "75", "label": "Café frappé", "color": "#c9824c" },
    { "num": "76", "label": "Marron glacé", "color": "#875124" },
    { "num": "77", "label": "Blanc calcaire", "color": "#dfd7d2" },
    { "num": "78", "label": "Pêche", "color": "#fbd2ac" },
    { "num": "79", "label": "Abricot", "color": "#f57d31" },
    { "num": "82", "label": "Prune", "color": "#941d53" },
    { "num": "83", "label": "Bleu pétrole", "color": "#056598" },
    { "num": "84", "label": "Vert olive", "color": "#6c742c" },
    { "num": "95", "label": "Rose clair pastel", "color": "#f5bcd1" },
    { "num": "96", "label": "Lilas pastel", "color": "#d3c1d9" },
    { "num": "97", "label": "Glacier pastel", "color": "#b3dff7" },
    { "num": "98", "label": "Menthe pastel", "color": "#c4decc" },
    { "num": "61", "label": "Or", "color": "#e3c594" },
    { "num": "62", "label": "Argent", "color": "#aaafb4" },
    { "num": "63", "label": "Bronze", "color": "#bcae80" },
    { "num": "65", "label": "Perle", "color": "#f6f7f4" }
  ]
}
